flask_nginx/__init__.py
flask_nginx/__main__.py
flask_nginx/asgi.py
flask_nginx/cli.py
flask_nginx/config.py
flask_nginx/core.py
flask_nginx/irds.py
flask_nginx/logo.py
flask_nginx/mailer.py
flask_nginx/mysql.py
flask_nginx/py.typed
flask_nginx/remote.py
flask_nginx/restartd.py
flask_nginx/rsync.py
flask_nginx/templating.py
flask_nginx/url.py
flask_nginx/utils.py
flask_nginx/watch.py
flask_nginx/systemd/__init__.py
flask_nginx/systemd/cli.py
flask_nginx/systemd/nginx.py
flask_nginx/systemd/supervisor.py
flask_nginx/systemd/systemd.py
flask_nginx/systemd/utils.py
flask_nginx/templates/celery.service
flask_nginx/templates/nginx-app.conf
flask_nginx/templates/nginx-test.conf
flask_nginx/templates/nginx-upstream.conf
flask_nginx/templates/nginx.conf
flask_nginx/templates/secure-tunnel.service
flask_nginx/templates/ssl.conf
flask_nginx/templates/supervisord.ini
flask_nginx/templates/systemd.mount
flask_nginx/templates/systemd.service
flask_nginx/templates/uvicorn.service
flask_nginx-0.8.15.dist-info/METADATA
flask_nginx-0.8.15.dist-info/WHEEL
flask_nginx-0.8.15.dist-info/entry_points.txt
flask_nginx-0.8.15.dist-info/RECORD
