Metadata-Version: 2.4
Name: flask-nginx
Version: 0.8.15
Summary: install flask websites into nginx
Author-email: arabidopsis <ian.castleden@uwa.edu.au>
Requires-Python: >=3.10
Requires-Dist: click<9,>=8
Requires-Dist: jinja2<4,>=3
Provides-Extra: psutil
Requires-Dist: psutil>=5.4; extra == 'psutil'
